aglfn/__init__.py
aglfn/agl.py
tests/__init__.py
tests/test_agl.py
tests/test_aglfn.py
aglfn-0.0.4.dist-info/LICENSE
aglfn-0.0.4.dist-info/METADATA
aglfn-0.0.4.dist-info/WHEEL
aglfn-0.0.4.dist-info/top_level.txt
aglfn-0.0.4.dist-info/RECORD
