Metadata-Version: 2.1
Name: aglfn
Version: 0.0.4
Summary: Python utilities for Adobe Glyph List For New Fonts
Home-page: UNKNOWN
Author: Puria Nafisi Azizi
Author-email: puria@dyne.org
License: Apache-2.0
Project-URL: Source Code, https://github.com/puria/aglfn
Keywords: words
Platform: UNKNOWN
Classifier: Development Status :: 3 - Alpha
Classifier: License :: OSI Approved :: Apache Software License
Classifier: Intended Audience :: Developers
Classifier: Operating System :: POSIX :: Linux
Classifier: Operating System :: MacOS :: MacOS X
Classifier: Programming Language :: Python
Provides-Extra: test
Requires-Dist: pytest ; extra == 'test'
Requires-Dist: pytest-cov ; extra == 'test'
